env/bin/rst2html.py
env/bin/rst2html4.py
env/bin/rst2html5.py
env/bin/rst2latex.py
env/bin/rst2man.py
env/bin/rst2odt.py
env/bin/rst2odt_prepstyles.py
env/bin/rst2pseudoxml.py
env/bin/rst2s5.py
env/bin/rst2xetex.py
env/bin/rst2xml.py
env/bin/rstpep2html.py
inmanta_plugins/ansible/__init__.py
inmanta_plugins/ansible/setup.cfg
inmanta_plugins/ansible/model/_init.cf
irt/setup.py
irt/build/lib/irt/__init__.py
irt/build/lib/irt/changelog.py
irt/build/lib/irt/config.py
irt/build/lib/irt/const.py
irt/build/lib/irt/credentials.py
irt/build/lib/irt/dep_merge.py
irt/build/lib/irt/git.py
irt/build/lib/irt/main.py
irt/build/lib/irt/module_sources.py
irt/build/lib/irt/modules.py
irt/build/lib/irt/project.py
irt/build/lib/irt/util.py
irt/build/lib/irt/version.py
irt/build/lib/irt/mergetool/__init__.py
irt/build/lib/irt/mergetool/config.py
irt/build/lib/irt/mergetool/github.py
irt/build/lib/irt/release/__init__.py
irt/build/lib/irt/release/build.py
irt/build/lib/irt/release/documentation.py
irt/build/lib/irt/release/modules.py
irt/build/lib/irt/release/release.py
irt/irt/__init__.py
irt/irt/changelog.py
irt/irt/config.py
irt/irt/const.py
irt/irt/credentials.py
irt/irt/dep_merge.py
irt/irt/git.py
irt/irt/main.py
irt/irt/module_sources.py
irt/irt/modules.py
irt/irt/project.py
irt/irt/util.py
irt/irt/version.py
irt/irt/graph-reporter/src/__init__.py
irt/irt/graph-reporter/src/main.py
irt/irt/label-sync/src/github_label_sync.py
irt/irt/label-sync/src/sync.py
irt/irt/mergetool/__init__.py
irt/irt/mergetool/config.py
irt/irt/mergetool/github.py
irt/irt/release/__init__.py
irt/irt/release/build.py
irt/irt/release/documentation.py
irt/irt/release/modules.py
irt/irt/release/release.py
irt/scripts/docs/setlastest.py
irt/tests/conftest.py
irt/tests/test_build.py
irt/tests/test_changelog.py
irt/tests/test_create_freeze_file.py
irt/tests/test_git.py
irt/tests/test_mergetool.py
irt/tests/test_model.py
irt/tests/test_module_checkout.py
irt/tests/test_module_release.py
irt/tests/test_project.py
inmanta_module_ansible-0.2.1.dist-info/METADATA
inmanta_module_ansible-0.2.1.dist-info/WHEEL
inmanta_module_ansible-0.2.1.dist-info/top_level.txt
inmanta_module_ansible-0.2.1.dist-info/RECORD
