Metadata-Version: 2.1
Name: inmanta-module-ansible
Version: 0.2.1
Summary: UNKNOWN
Home-page: UNKNOWN
License: Apache 2.0
Platform: UNKNOWN
Requires-Dist: inmanta-module-std
